loxodrome-0.0.1.dist-info/METADATA
loxodrome-0.0.1.dist-info/WHEEL
loxodrome-0.0.1.dist-info/entry_points.txt
loxodrome/__init__.py
loxodrome/_loxodrome_rs.cpython-312-x86_64-linux-gnu.so
loxodrome/_loxodrome_rs.pyi
loxodrome/cli.py
loxodrome/errors.py
loxodrome/ext/__init__.py
loxodrome/ext/shapely.py
loxodrome/geometry.py
loxodrome/ops.py
loxodrome/py.typed
loxodrome/types.py
loxodrome/vectorized.py
loxodrome-0.0.1.dist-info/RECORD
