Metadata-Version: 2.4
Name: loxodrome
Version: 0.0.1
Classifier: Development Status :: 4 - Beta
Classifier: Intended Audience :: Developers
Classifier: Operating System :: OS Independent
Classifier: Programming Language :: Python
Classifier: Programming Language :: Python :: 3
Classifier: Programming Language :: Python :: 3.10
Classifier: Programming Language :: Python :: 3.11
Classifier: Programming Language :: Python :: 3.12
Classifier: Programming Language :: Python :: 3.13
Classifier: Typing :: Typed
Requires-Dist: typing-extensions>=4.12.2
Requires-Dist: shapely>=2.0,<3.0 ; extra == 'shapely'
Requires-Dist: numpy>=1.24 ; extra == 'vectorized'
Provides-Extra: shapely
Provides-Extra: vectorized
Summary: Geodesic distance and Hausdorff kernels with Rust performance and Python usability.
Author-email: Edward Jones <e@eddie.land>
License-Expression: MIT
Requires-Python: >=3.10, <4.0
Project-URL: Repository, https://github.com/eddieland/loxodrome
